AthenaLib/__init__.py
AthenaLib/Decorators/__init__.py
AthenaLib/Decorators/event_waiter.py
AthenaLib/Fixes/Asyncio.py
AthenaLib/Fixes/__init__.py
AthenaLib/HTML/__init__.py
AthenaLib/HTML/data/__init__.py
AthenaLib/HTML/data/css_selection_type.py
AthenaLib/HTML/models/__init__.py
AthenaLib/HTML/models/css.py
AthenaLib/HTML/models/html.py
AthenaLib/HTML/models/html_library.py
AthenaLib/HTML/models/html_library_unsupported_in_html_5.py
AthenaLib/HTTP/__init__.py
AthenaLib/HTTP/functions/__init__.py
AthenaLib/HTTP/functions/requests.py
AthenaLib/data/__init__.py
AthenaLib/data/text.py
AthenaLib/functions/__init__.py
AthenaLib/functions/class_from_method.py
AthenaLib/functions/dunder_math.py
AthenaLib/functions/random.py
AthenaLib/functions/slicing.py
AthenaLib/functions/string.py
AthenaLib/functions/time.py
AthenaLib/functions/type_check.py
AthenaLib/models/__init__.py
AthenaLib/models/bezier.py
AthenaLib/models/degree.py
AthenaLib/models/length_absolute.py
AthenaLib/models/length_relative.py
AthenaLib/models/percent.py
AthenaLib/models/time.py
AthenaLib/models/url.py
AthenaLib/models/vectors.py
AthenaLib/models/version.py
AthenaLib-1.6.0.dist-info/LICENSE
AthenaLib-1.6.0.dist-info/METADATA
AthenaLib-1.6.0.dist-info/WHEEL
AthenaLib-1.6.0.dist-info/top_level.txt
AthenaLib-1.6.0.dist-info/RECORD
