Metadata-Version: 2.1
Name: AthenaLib
Version: 1.6.0
Summary: A Library for Directive Athena related Python Packages
Home-page: https://github.com/DirectiveAthena/AthenaLib
Author: Andreas Sas
Author-email: 
License: GPLv3
Project-URL: Bug Tracker, https://github.com/DirectiveAthena/AthenaLib/issues
Requires-Python: >=3.10
License-File: LICENSE
Requires-Dist: AthenaColor (>=6.2.0)
